{
  "date": "2026-05-07",
  "summaries": [
    {
      "filename": "mexicolife.com-organic.PositionChangesV2-us-20260506-2026-05-07T07_10_11Z.csv",
      "competitorId": "www-mexicolife-com",
      "type": "positions",
      "rowCount": 1898,
      "topRows": [
        {
          "Keyword": "puerto vallarta homes for sale",
          "Position": "18",
          "Previous position": "3",
          "Search Volume": "2900",
          "Keyword Difficulty": "21",
          "CPC": "0.19",
          "Keyword Intents": "transactional",
          "URL": "https://www.mexicolife.com/puerto-vallarta-real-estate.php",
          "Traffic Change": "-229",
          "Traffic (%)": "0.21",
          "Traffic Cost": "1.00",
          "Competition": "0.36",
          "Number of Results": "889000",
          "Trends": "[100,81,66,53,53,44,44,53,53,24,44,24]",
          "Timestamp": "2026-05-06",
          "Position Type": "Organic",
          "Keyword SERP Features (New)": "",
          "Keyword SERP Features (Lost)": ""
        },
        {
          "Keyword": "puerto vallarta condos for sale",
          "Position": "33",
          "Previous position": "2",
          "Search Volume": "1300",
          "Keyword Difficulty": "10",
          "CPC": "0.24",
          "Keyword Intents": "transactional",
          "URL": "https://www.mexicolife.com/beachfront-condos-for-sale-in-puerto-vallarta.php",
          "Traffic Change": "-171",
          "Traffic (%)": "0",
          "Traffic Cost": "0.00",
          "Competition": "0.41",
          "Number of Results": "117",
          "Trends": "[82,44,34,55,55,55,55,30,30,24,34,20]",
          "Timestamp": "2026-04-21",
          "Position Type": "Organic",
          "Keyword SERP Features (New)": "",
          "Keyword SERP Features (Lost)": "People also ask"
        },
        {
          "Keyword": "condos for sale in puerto vallarta mexico",
          "Position": "26",
          "Previous position": "2",
          "Search Volume": "1000",
          "Keyword Difficulty": "5",
          "CPC": "0.24",
          "Keyword Intents": "transactional",
          "URL": "https://www.mexicolife.com/beachfront-condos-for-sale-in-puerto-vallarta.php",
          "Traffic Change": "-132",
          "Traffic (%)": "0",
          "Traffic Cost": "0.00",
          "Competition": "0.41",
          "Number of Results": "436000",
          "Trends": "[62,81,81,100,45,45,62,55,45,45,45,81]",
          "Timestamp": "2026-04-24",
          "Position Type": "Organic",
          "Keyword SERP Features (New)": "",
          "Keyword SERP Features (Lost)": ""
        },
        {
          "Keyword": "puerto vallarta real estate",
          "Position": "0",
          "Previous position": "6",
          "Search Volume": "3600",
          "Keyword Difficulty": "35",
          "CPC": "0.20",
          "Keyword Intents": "commercial",
          "URL": "https://www.mexicolife.com/puerto-vallarta-real-estate.php",
          "Traffic Change": "-126",
          "Traffic (%)": "0",
          "Traffic Cost": "0.00",
          "Competition": "0.44",
          "Number of Results": "4580000",
          "Trends": "[81,81,66,54,66,54,66,54,43,36,36,28]",
          "Timestamp": "2026-04-26",
          "Position Type": "Organic",
          "Keyword SERP Features (New)": "",
          "Keyword SERP Features (Lost)": ""
        },
        {
          "Keyword": "nuevo vallarta mexico",
          "Position": "1",
          "Previous position": "0",
          "Search Volume": "1000",
          "Keyword Difficulty": "20",
          "CPC": "0.82",
          "Keyword Intents": "informational",
          "URL": "https://www.mexicolife.com/nuevo-vallarta-condos-for-sale.php",
          "Traffic Change": "124",
          "Traffic (%)": "3.4",
          "Traffic Cost": "101.00",
          "Competition": "0.15",
          "Number of Results": "104",
          "Trends": "[46,100,37,37,37,46,52,52,46,46,46,52]",
          "Timestamp": "2026-04-21",
          "Position Type": "Things to know",
          "Keyword SERP Features (New)": "",
          "Keyword SERP Features (Lost)": ""
        },
        {
          "Keyword": "puerto vallarta real estate",
          "Position": "4",
          "Previous position": "22",
          "Search Volume": "3600",
          "Keyword Difficulty": "43",
          "CPC": "0.20",
          "Keyword Intents": "commercial",
          "URL": "https://www.mexicolife.com/old-town-vallarta.php",
          "Traffic Change": "103",
          "Traffic (%)": "2.96",
          "Traffic Cost": "21.00",
          "Competition": "0.44",
          "Number of Results": "3540000",
          "Trends": "[81,81,66,54,66,54,66,54,43,36,36,28]",
          "Timestamp": "2026-05-03",
          "Position Type": "Organic",
          "Keyword SERP Features (New)": "People also ask",
          "Keyword SERP Features (Lost)": ""
        },
        {
          "Keyword": "houses for sale puerto vallarta",
          "Position": "0",
          "Previous position": "3",
          "Search Volume": "880",
          "Keyword Difficulty": "14",
          "CPC": "0.19",
          "Keyword Intents": "transactional",
          "URL": "https://www.mexicolife.com/idx/",
          "Traffic Change": "-72",
          "Traffic (%)": "0",
          "Traffic Cost": "0.00",
          "Competition": "0.36",
          "Number of Results": "1800000",
          "Trends": "[100,27,10,10,10,13,13,8,8,10,52,1]",
          "Timestamp": "2026-05-05",
          "Position Type": "Organic",
          "Keyword SERP Features (New)": "",
          "Keyword SERP Features (Lost)": ""
        },
        {
          "Keyword": "condos for sale in puerto vallarta mexico",
          "Position": "4",
          "Previous position": "0",
          "Search Volume": "1000",
          "Keyword Difficulty": "5",
          "CPC": "0.24",
          "Keyword Intents": "transactional",
          "URL": "https://www.mexicolife.com/puerto-vallarta-condos-for-sale.php",
          "Traffic Change": "65",
          "Traffic (%)": "1.78",
          "Traffic Cost": "15.00",
          "Competition": "0.41",
          "Number of Results": "436000",
          "Trends": "[62,81,81,100,45,45,62,55,45,45,45,81]",
          "Timestamp": "2026-04-24",
          "Position Type": "Organic",
          "Keyword SERP Features (New)": "",
          "Keyword SERP Features (Lost)": ""
        },
        {
          "Keyword": "vallarta condos",
          "Position": "38",
          "Previous position": "1",
          "Search Volume": "260",
          "Keyword Difficulty": "13",
          "CPC": "0.70",
          "Keyword Intents": "commercial",
          "URL": "https://www.mexicolife.com/puerto-vallarta-condos-for-sale.php",
          "Traffic Change": "-64",
          "Traffic (%)": "0",
          "Traffic Cost": "0.00",
          "Competition": "0.55",
          "Number of Results": "723000",
          "Trends": "[54,35,35,66,100,81,28,28,54,44,0,0]",
          "Timestamp": "2026-04-27",
          "Position Type": "Organic",
          "Keyword SERP Features (New)": "",
          "Keyword SERP Features (Lost)": ""
        },
        {
          "Keyword": "bucerias",
          "Position": "0",
          "Previous position": "1",
          "Search Volume": "2900",
          "Keyword Difficulty": "33",
          "CPC": "1.21",
          "Keyword Intents": "informational",
          "URL": "https://www.mexicolife.com/puerto-vallarta-vs-bucerias.php",
          "Traffic Change": "-63",
          "Traffic (%)": "0",
          "Traffic Cost": "0.00",
          "Competition": "0.09",
          "Number of Results": "128",
          "Trends": "[100,66,81,66,44,44,44,35,29,35,44,53]",
          "Timestamp": "2026-04-14",
          "Position Type": "People also ask",
          "Keyword SERP Features (New)": "",
          "Keyword SERP Features (Lost)": ""
        },
        {
          "Keyword": "puerto vallarta real estate condos for sale",
          "Position": "2",
          "Previous position": "0",
          "Search Volume": "480",
          "Keyword Difficulty": "10",
          "CPC": "0.24",
          "Keyword Intents": "transactional",
          "URL": "https://www.mexicolife.com/puerto-vallarta-condos-for-sale.php",
          "Traffic Change": "63",
          "Traffic (%)": "1.73",
          "Traffic Cost": "15.00",
          "Competition": "0.41",
          "Number of Results": "346000",
          "Trends": "[5,7,4,3,11,25,100,37,68,52,5,5]",
          "Timestamp": "2026-05-06",
          "Position Type": "Organic",
          "Keyword SERP Features (New)": "",
          "Keyword SERP Features (Lost)": ""
        },
        {
          "Keyword": "homes for sale puerto vallarta",
          "Position": "14",
          "Previous position": "4",
          "Search Volume": "880",
          "Keyword Difficulty": "17",
          "CPC": "0.19",
          "Keyword Intents": "transactional",
          "URL": "https://www.mexicolife.com/puerto-vallarta-real-estate.php",
          "Traffic Change": "-61",
          "Traffic (%)": "0.1",
          "Traffic Cost": "0.00",
          "Competition": "0.36",
          "Number of Results": "106",
          "Trends": "[44,27,24,24,24,36,24,20,16,10,8,10]",
          "Timestamp": "2026-04-15",
          "Position Type": "Organic",
          "Keyword SERP Features (New)": "",
          "Keyword SERP Features (Lost)": "People also ask"
        },
        {
          "Keyword": "mexico real estate",
          "Position": "0",
          "Previous position": "3",
          "Search Volume": "2900",
          "Keyword Difficulty": "42",
          "CPC": "0.31",
          "Keyword Intents": "commercial, informational",
          "URL": "https://www.mexicolife.com/blog/buying-property-in-mexicos-restricted-zone-complete-faq-for-foreign-buyers.html",
          "Traffic Change": "-50",
          "Traffic (%)": "0",
          "Traffic Cost": "0.00",
          "Competition": "0.2",
          "Number of Results": "367000000",
          "Trends": "[81,66,53,53,53,53,53,44,44,35,29,35]",
          "Timestamp": "2026-05-06",
          "Position Type": "Things to know",
          "Keyword SERP Features (New)": "",
          "Keyword SERP Features (Lost)": ""
        },
        {
          "Keyword": "san pancho mexico real estate",
          "Position": "6",
          "Previous position": "2",
          "Search Volume": "390",
          "Keyword Difficulty": "12",
          "CPC": "0.11",
          "Keyword Intents": "commercial",
          "URL": "https://www.mexicolife.com/san-pancho-mls.php",
          "Traffic Change": "-42",
          "Traffic (%)": "0.24",
          "Traffic Cost": "0.00",
          "Competition": "0.27",
          "Number of Results": "621000",
          "Trends": "[100,81,100,66,66,66,66,66,54,54,66,66]",
          "Timestamp": "2026-04-15",
          "Position Type": "Organic",
          "Keyword SERP Features (New)": "",
          "Keyword SERP Features (Lost)": "People also ask"
        },
        {
          "Keyword": "puerto vallarta condo for sale",
          "Position": "32",
          "Previous position": "2",
          "Search Volume": "210",
          "Keyword Difficulty": "11",
          "CPC": "0.24",
          "Keyword Intents": "transactional",
          "URL": "https://www.mexicolife.com/beachfront-condos-for-sale-in-puerto-vallarta.php",
          "Traffic Change": "-42",
          "Traffic (%)": "0",
          "Traffic Cost": "0.00",
          "Competition": "0.41",
          "Number of Results": "474000",
          "Trends": "[10,16,55,36,1,1,10,3,36,24,5,6]",
          "Timestamp": "2026-04-19",
          "Position Type": "Organic",
          "Keyword SERP Features (New)": "",
          "Keyword SERP Features (Lost)": "People also ask"
        },
        {
          "Keyword": "pier 57 puerto vallarta",
          "Position": "18",
          "Previous position": "6",
          "Search Volume": "1000",
          "Keyword Difficulty": "22",
          "CPC": "1.41",
          "Keyword Intents": "informational",
          "URL": "https://www.mexicolife.com/puerto-vallarta-centro-south-pier-57.php",
          "Traffic Change": "-34",
          "Traffic (%)": "0.02",
          "Traffic Cost": "1.00",
          "Competition": "0.85",
          "Number of Results": "326000",
          "Trends": "[84,52,52,100,68,46,37,37,25,31,46,46]",
          "Timestamp": "2026-04-25",
          "Position Type": "Organic",
          "Keyword SERP Features (New)": "Local pack",
          "Keyword SERP Features (Lost)": "Knowledge panel, Short videos"
        },
        {
          "Keyword": "condo for sale puerto vallarta",
          "Position": "3",
          "Previous position": "0",
          "Search Volume": "390",
          "Keyword Difficulty": "5",
          "CPC": "0.24",
          "Keyword Intents": "transactional",
          "URL": "https://www.mexicolife.com/puerto-vallarta-condos-for-sale-zona-romantica.php",
          "Traffic Change": "31",
          "Traffic (%)": "0.85",
          "Traffic Cost": "7.00",
          "Competition": "0.41",
          "Number of Results": "449000",
          "Trends": "[15,54,54,36,44,44,54,23,29,44,29,44]",
          "Timestamp": "2026-04-30",
          "Position Type": "Organic",
          "Keyword SERP Features (New)": "",
          "Keyword SERP Features (Lost)": ""
        },
        {
          "Keyword": "condo for sale puerto vallarta",
          "Position": "26",
          "Previous position": "3",
          "Search Volume": "390",
          "Keyword Difficulty": "5",
          "CPC": "0.24",
          "Keyword Intents": "transactional",
          "URL": "https://www.mexicolife.com/beachfront-condos-for-sale-in-puerto-vallarta.php",
          "Traffic Change": "-31",
          "Traffic (%)": "0",
          "Traffic Cost": "0.00",
          "Competition": "0.41",
          "Number of Results": "449000",
          "Trends": "[15,54,54,36,44,44,54,23,29,44,29,44]",
          "Timestamp": "2026-04-30",
          "Position Type": "Organic",
          "Keyword SERP Features (New)": "People also ask",
          "Keyword SERP Features (Lost)": ""
        },
        {
          "Keyword": "puerto vallarta condos for sale",
          "Position": "9",
          "Previous position": "0",
          "Search Volume": "1300",
          "Keyword Difficulty": "10",
          "CPC": "0.24",
          "Keyword Intents": "transactional",
          "URL": "https://www.mexicolife.com/puerto-vallarta-condos-for-sale-zona-romantica.php",
          "Traffic Change": "31",
          "Traffic (%)": "0.85",
          "Traffic Cost": "7.00",
          "Competition": "0.41",
          "Number of Results": "117",
          "Trends": "[82,44,34,55,55,55,55,30,30,24,34,20]",
          "Timestamp": "2026-04-21",
          "Position Type": "Organic",
          "Keyword SERP Features (New)": "",
          "Keyword SERP Features (Lost)": ""
        },
        {
          "Keyword": "puerto vallarta mexico condos",
          "Position": "0",
          "Previous position": "2",
          "Search Volume": "210",
          "Keyword Difficulty": "17",
          "CPC": "0.60",
          "Keyword Intents": "commercial",
          "URL": "https://www.mexicolife.com/beachfront-condos-for-sale-in-puerto-vallarta.php",
          "Traffic Change": "-27",
          "Traffic (%)": "0",
          "Traffic Cost": "0.00",
          "Competition": "0.54",
          "Number of Results": "288000",
          "Trends": "[15,11,0,35,66,100,35,18,28,44,44,1]",
          "Timestamp": "2026-04-21",
          "Position Type": "Organic",
          "Keyword SERP Features (New)": "",
          "Keyword SERP Features (Lost)": ""
        },
        {
          "Keyword": "puerto vallarta mexico condos",
          "Position": "2",
          "Previous position": "21",
          "Search Volume": "210",
          "Keyword Difficulty": "5",
          "CPC": "0.70",
          "Keyword Intents": "commercial",
          "URL": "https://www.mexicolife.com/puerto-vallarta-condos-for-sale.php",
          "Traffic Change": "27",
          "Traffic (%)": "0.74",
          "Traffic Cost": "18.00",
          "Competition": "0.55",
          "Number of Results": "614000",
          "Trends": "[11,0,35,66,100,35,18,28,44,44,1,6]",
          "Timestamp": "2026-04-21",
          "Position Type": "Organic",
          "Keyword SERP Features (New)": "",
          "Keyword SERP Features (Lost)": "People also ask"
        },
        {
          "Keyword": "cheap homes for sale in mexico",
          "Position": "3",
          "Previous position": "0",
          "Search Volume": "320",
          "Keyword Difficulty": "16",
          "CPC": "0.98",
          "Keyword Intents": "transactional",
          "URL": "https://www.mexicolife.com/pool/under-100000/",
          "Traffic Change": "26",
          "Traffic (%)": "0.71",
          "Traffic Cost": "25.00",
          "Competition": "0.05",
          "Number of Results": "83600000",
          "Trends": "[72,48,39,39,21,21,39,26,21,17,17,21]",
          "Timestamp": "2026-05-05",
          "Position Type": "Organic",
          "Keyword SERP Features (New)": "",
          "Keyword SERP Features (Lost)": ""
        },
        {
          "Keyword": "cheap houses for sale in mexico",
          "Position": "3",
          "Previous position": "0",
          "Search Volume": "320",
          "Keyword Difficulty": "9",
          "CPC": "0.98",
          "Keyword Intents": "transactional",
          "URL": "https://www.mexicolife.com/pool/under-100000/",
          "Traffic Change": "26",
          "Traffic (%)": "0.71",
          "Traffic Cost": "25.00",
          "Competition": "0.05",
          "Number of Results": "71300000",
          "Trends": "[54,54,54,54,44,44,54,44,44,29,29,36]",
          "Timestamp": "2026-05-06",
          "Position Type": "Organic",
          "Keyword SERP Features (New)": "",
          "Keyword SERP Features (Lost)": ""
        },
        {
          "Keyword": "mexico realty",
          "Position": "12",
          "Previous position": "5",
          "Search Volume": "720",
          "Keyword Difficulty": "26",
          "CPC": "0.31",
          "Keyword Intents": "commercial",
          "URL": "https://www.mexicolife.com/",
          "Traffic Change": "-25",
          "Traffic (%)": "0.16",
          "Traffic Cost": "1.00",
          "Competition": "0.2",
          "Number of Results": "30600000",
          "Trends": "[62,45,6,62,45,45,100,30,55,36,24,36]",
          "Timestamp": "2026-05-05",
          "Position Type": "Organic",
          "Keyword SERP Features (New)": "",
          "Keyword SERP Features (Lost)": ""
        },
        {
          "Keyword": "chacala mexico",
          "Position": "0",
          "Previous position": "7",
          "Search Volume": "1900",
          "Keyword Difficulty": "17",
          "CPC": "0.91",
          "Keyword Intents": "informational",
          "URL": "https://www.mexicolife.com/nayarit/chacala.php",
          "Traffic Change": "-24",
          "Traffic (%)": "0",
          "Traffic Cost": "0.00",
          "Competition": "0.08",
          "Number of Results": "534000",
          "Trends": "[54,79,100,79,79,79,79,66,66,54,66,79]",
          "Timestamp": "2026-04-14",
          "Position Type": "Organic",
          "Keyword SERP Features (New)": "",
          "Keyword SERP Features (Lost)": ""
        }
      ]
    },
    {
      "filename": "mexicolife.com-backlinks.csv",
      "competitorId": "www-mexicolife-com",
      "type": "backlinks",
      "rowCount": 51,
      "topRows": [
        {
          "Page ascore": "13",
          "Source title": "Page 287 – Mexico News Daily",
          "Source url": "https://mexiconewsdaily.com/page/287/?p=sendPageLink&value=https%3A%2F%2Fthenewsbizz.site",
          "Target url": "https://www.mexicolife.com/blog/puerto-vallarta-house-market-report-march-2025.html",
          "Anchor": "Mexico Life Realty",
          "External links": "61",
          "Internal links": "118",
          "Nofollow": "false",
          "Sponsored": "false",
          "Ugc": "false",
          "Text": "true",
          "Frame": "false",
          "Form": "false",
          "Image": "false",
          "Sitewide": "false",
          "First seen": "2026-05-06",
          "Last seen": "2026-05-06",
          "New link": "true",
          "Lost link": "false"
        },
        {
          "Page ascore": "18",
          "Source title": "How Much Does a House Cost in Mexico in 2026: The Ultimate Guide | Remitly",
          "Source url": "https://www.remitly.com/blog/finance/how-much-is-a-house-in-mexico/",
          "Target url": "https://www.mexicolife.com/blog/mexico-real-estate-closing-costs-2025.html",
          "Anchor": "range from",
          "External links": "26",
          "Internal links": "108",
          "Nofollow": "false",
          "Sponsored": "false",
          "Ugc": "false",
          "Text": "true",
          "Frame": "false",
          "Form": "false",
          "Image": "false",
          "Sitewide": "false",
          "First seen": "2026-05-06",
          "Last seen": "2026-05-06",
          "New link": "true",
          "Lost link": "false"
        },
        {
          "Page ascore": "0",
          "Source title": "Where to buy 🚀 aged domains and backlinks 🔥 | 6362-3474",
          "Source url": "https://indexaward.com/6edbdfa3ca623474b978382aedaa00af-l/",
          "Target url": "https://mexicolife.com/",
          "Anchor": "mexicolife.com",
          "External links": "9003",
          "Internal links": "12",
          "Nofollow": "false",
          "Sponsored": "false",
          "Ugc": "false",
          "Text": "true",
          "Frame": "false",
          "Form": "false",
          "Image": "false",
          "Sitewide": "false",
          "First seen": "2026-05-05",
          "Last seen": "2026-05-05",
          "New link": "true",
          "Lost link": "false"
        },
        {
          "Page ascore": "0",
          "Source title": "Where to buy 🚀 aged domains and backlinks 🔥 from mail.domainanalysis.org | 0370-5882",
          "Source url": "https://mail.domainanalysis.org/page-0b3fc7f0588fcac214841501c1f573e5.html",
          "Target url": "https://mexicolife.com/",
          "Anchor": "homeinmexico.com",
          "External links": "10158",
          "Internal links": "13",
          "Nofollow": "false",
          "Sponsored": "false",
          "Ugc": "false",
          "Text": "true",
          "Frame": "false",
          "Form": "false",
          "Image": "false",
          "Sitewide": "false",
          "First seen": "2026-05-03",
          "Last seen": "2026-05-03",
          "New link": "true",
          "Lost link": "false"
        },
        {
          "Page ascore": "0",
          "Source title": "Where to buy 🚀 aged domains and backlinks 🔥 from mail.allwebsitesdirectory.com | 8834-0831",
          "Source url": "https://mail.allwebsitesdirectory.com/page-8b8f340a83d169a77d3491375a781936.html",
          "Target url": "https://mexicolife.com/",
          "Anchor": "mexicolife.com",
          "External links": "10159",
          "Internal links": "13",
          "Nofollow": "false",
          "Sponsored": "false",
          "Ugc": "false",
          "Text": "true",
          "Frame": "false",
          "Form": "false",
          "Image": "false",
          "Sitewide": "false",
          "First seen": "2026-05-03",
          "Last seen": "2026-05-03",
          "New link": "true",
          "Lost link": "false"
        },
        {
          "Page ascore": "0",
          "Source title": "Best Tool for Pinterest SiteToSocial Fully Automated AI Generated Pins Grow Your Website Traffic",
          "Source url": "https://newsblogsports.site/all/231/23",
          "Target url": "https://mexicolife.com/",
          "Anchor": "Best Pinterest Tool SiteToSocial.com to Grow Your Website Traffic Fully Automated",
          "External links": "3004",
          "Internal links": "24",
          "Nofollow": "false",
          "Sponsored": "false",
          "Ugc": "false",
          "Text": "true",
          "Frame": "false",
          "Form": "false",
          "Image": "false",
          "Sitewide": "false",
          "First seen": "2026-05-02",
          "Last seen": "2026-05-02",
          "New link": "true",
          "Lost link": "false"
        },
        {
          "Page ascore": "0",
          "Source title": "Where to buy 🚀 aged domains and backlinks 🔥 from www.domainsc.com | 0433-4886",
          "Source url": "https://www.domainsc.com/page-0433488a64ac643080dec84f998e8f89.html",
          "Target url": "https://www.mexicolife.com/",
          "Anchor": "ergmex.com",
          "External links": "10159",
          "Internal links": "13",
          "Nofollow": "false",
          "Sponsored": "false",
          "Ugc": "false",
          "Text": "true",
          "Frame": "false",
          "Form": "false",
          "Image": "false",
          "Sitewide": "false",
          "First seen": "2026-04-30",
          "Last seen": "2026-04-30",
          "New link": "true",
          "Lost link": "false"
        },
        {
          "Page ascore": "0",
          "Source title": "Where to buy 🚀 aged domains and backlinks 🔥 from mail.linksnatcher.com | 0370-5882",
          "Source url": "https://mail.linksnatcher.com/page-0b3fc7f0588fcac214841501c1f573e5.html",
          "Target url": "https://mexicolife.com/",
          "Anchor": "homeinmexico.com",
          "External links": "10158",
          "Internal links": "12",
          "Nofollow": "false",
          "Sponsored": "false",
          "Ugc": "false",
          "Text": "true",
          "Frame": "false",
          "Form": "false",
          "Image": "false",
          "Sitewide": "false",
          "First seen": "2026-04-29",
          "Last seen": "2026-04-29",
          "New link": "true",
          "Lost link": "false"
        },
        {
          "Page ascore": "0",
          "Source title": "Where to buy 🚀 aged domains and backlinks 🔥 | 4235-9593",
          "Source url": "https://pagesearch.net/acada423edbf5ef95d9314fb9a14163d-l/",
          "Target url": "https://www.mexicolife.com/",
          "Anchor": "ergmex.com",
          "External links": "9003",
          "Internal links": "12",
          "Nofollow": "false",
          "Sponsored": "false",
          "Ugc": "false",
          "Text": "true",
          "Frame": "false",
          "Form": "false",
          "Image": "false",
          "Sitewide": "false",
          "First seen": "2026-04-28",
          "Last seen": "2026-04-28",
          "New link": "true",
          "Lost link": "false"
        },
        {
          "Page ascore": "0",
          "Source title": "puerto vallarta real estate for sale old town",
          "Source url": "https://test.goldigkeit.de/r0xwzc/puerto-vallarta-real-estate-for-sale-old-town",
          "Target url": "https://www.mexicolife.com/old-town-vallarta.php",
          "Anchor": "",
          "External links": "15",
          "Internal links": "4",
          "Nofollow": "false",
          "Sponsored": "false",
          "Ugc": "false",
          "Text": "true",
          "Frame": "false",
          "Form": "false",
          "Image": "false",
          "Sitewide": "false",
          "First seen": "2026-04-28",
          "Last seen": "2026-04-28",
          "New link": "true",
          "Lost link": "false"
        },
        {
          "Page ascore": "0",
          "Source title": "Where to buy 🚀 aged domains and backlinks 🔥 from www.indians.cc | 8834-0831",
          "Source url": "https://www.indians.cc/page-8b8f340a83d169a77d3491375a781936.html",
          "Target url": "https://mexicolife.com/",
          "Anchor": "mexicolife.com",
          "External links": "10160",
          "Internal links": "12",
          "Nofollow": "false",
          "Sponsored": "false",
          "Ugc": "false",
          "Text": "true",
          "Frame": "false",
          "Form": "false",
          "Image": "false",
          "Sitewide": "false",
          "First seen": "2026-04-27",
          "Last seen": "2026-04-27",
          "New link": "true",
          "Lost link": "false"
        },
        {
          "Page ascore": "0",
          "Source title": "Where to buy 🚀 aged domains and backlinks 🔥 from read.org.in| 0433-4886",
          "Source url": "https://read.org.in/page-0433488a64ac643080dec84f998e8f89.html",
          "Target url": "https://www.mexicolife.com/",
          "Anchor": "ergmex.com",
          "External links": "10160",
          "Internal links": "12",
          "Nofollow": "false",
          "Sponsored": "false",
          "Ugc": "false",
          "Text": "true",
          "Frame": "false",
          "Form": "false",
          "Image": "false",
          "Sitewide": "false",
          "First seen": "2026-04-26",
          "Last seen": "2026-04-26",
          "New link": "true",
          "Lost link": "false"
        },
        {
          "Page ascore": "0",
          "Source title": "Where to buy 🚀 aged domains and backlinks 🔥 from www.pudhe.com | 0370-5882",
          "Source url": "https://www.pudhe.com/page-0b3fc7f0588fcac214841501c1f573e5.html",
          "Target url": "https://mexicolife.com/",
          "Anchor": "homeinmexico.com",
          "External links": "10158",
          "Internal links": "13",
          "Nofollow": "false",
          "Sponsored": "false",
          "Ugc": "false",
          "Text": "true",
          "Frame": "false",
          "Form": "false",
          "Image": "false",
          "Sitewide": "false",
          "First seen": "2026-04-25",
          "Last seen": "2026-04-25",
          "New link": "true",
          "Lost link": "false"
        },
        {
          "Page ascore": "0",
          "Source title": "Where to buy 🚀 aged domains and backlinks 🔥 from www.domain.com.lc | 0433-4886",
          "Source url": "https://www.domain.com.lc/page-0433488a64ac643080dec84f998e8f89.html",
          "Target url": "https://www.mexicolife.com/",
          "Anchor": "ergmex.com",
          "External links": "10159",
          "Internal links": "13",
          "Nofollow": "false",
          "Sponsored": "false",
          "Ugc": "false",
          "Text": "true",
          "Frame": "false",
          "Form": "false",
          "Image": "false",
          "Sitewide": "false",
          "First seen": "2026-04-25",
          "Last seen": "2026-05-04",
          "New link": "true",
          "Lost link": "false"
        },
        {
          "Page ascore": "0",
          "Source title": "Boost Organic Traffic, Rankings & Authority with 100% Premium Backlinks 🎖️ – Give Your Competitors a Tough Time! 💪 | Rankvance.com",
          "Source url": "https://rankvanceseo.info/get-affordable-premium-backlinks-from-rankvance-with-discounted-rates-393/",
          "Target url": "https://mexicolife.com/",
          "Anchor": "puertovallartarealestate.com",
          "External links": "2001",
          "Internal links": "36",
          "Nofollow": "false",
          "Sponsored": "false",
          "Ugc": "false",
          "Text": "true",
          "Frame": "false",
          "Form": "false",
          "Image": "false",
          "Sitewide": "false",
          "First seen": "2026-04-25",
          "Last seen": "2026-04-25",
          "New link": "true",
          "Lost link": "false"
        },
        {
          "Page ascore": "0",
          "Source title": "Where to buy 🚀 aged domains and backlinks 🔥 from mail.bestwebstats.com | 0433-4886",
          "Source url": "https://mail.bestwebstats.com/page-0433488a64ac643080dec84f998e8f89.html",
          "Target url": "https://www.mexicolife.com/",
          "Anchor": "ergmex.com",
          "External links": "10159",
          "Internal links": "13",
          "Nofollow": "false",
          "Sponsored": "false",
          "Ugc": "false",
          "Text": "true",
          "Frame": "false",
          "Form": "false",
          "Image": "false",
          "Sitewide": "false",
          "First seen": "2026-04-23",
          "Last seen": "2026-04-23",
          "New link": "true",
          "Lost link": "false"
        },
        {
          "Page ascore": "0",
          "Source title": "Where to buy 🚀 aged domains and backlinks 🔥 from www.alltopleveldomains.space| 3759-4034",
          "Source url": "http://www.alltopleveldomains.space/page-3d759403f4619039451bcce2ad5b5a15.html",
          "Target url": "https://mexicolife.com/",
          "Anchor": "caribbeanbestrealestate.com",
          "External links": "10160",
          "Internal links": "12",
          "Nofollow": "false",
          "Sponsored": "false",
          "Ugc": "false",
          "Text": "true",
          "Frame": "false",
          "Form": "false",
          "Image": "false",
          "Sitewide": "false",
          "First seen": "2026-04-22",
          "Last seen": "2026-04-22",
          "New link": "true",
          "Lost link": "false"
        },
        {
          "Page ascore": "0",
          "Source title": "Where to buy 🚀 aged domains and backlinks 🔥 from www.theface.in| 3759-4034",
          "Source url": "http://www.theface.in/page-3d759403f4619039451bcce2ad5b5a15.html",
          "Target url": "https://mexicolife.com/",
          "Anchor": "caribbeanbestrealestate.com",
          "External links": "10160",
          "Internal links": "12",
          "Nofollow": "false",
          "Sponsored": "false",
          "Ugc": "false",
          "Text": "true",
          "Frame": "false",
          "Form": "false",
          "Image": "false",
          "Sitewide": "false",
          "First seen": "2026-04-22",
          "Last seen": "2026-04-22",
          "New link": "true",
          "Lost link": "false"
        },
        {
          "Page ascore": "0",
          "Source title": "Where to buy 🚀 aged domains and backlinks 🔥 | 6362-3474",
          "Source url": "https://mail.wallpapers.pro/6edbdfa3ca623474b978382aedaa00af-l/",
          "Target url": "https://mexicolife.com/",
          "Anchor": "mexicolife.com",
          "External links": "9002",
          "Internal links": "13",
          "Nofollow": "false",
          "Sponsored": "false",
          "Ugc": "false",
          "Text": "true",
          "Frame": "false",
          "Form": "false",
          "Image": "false",
          "Sitewide": "false",
          "First seen": "2026-04-22",
          "Last seen": "2026-04-30",
          "New link": "true",
          "Lost link": "false"
        },
        {
          "Page ascore": "0",
          "Source title": "Where to buy 🚀 aged domains and backlinks 🔥 from www.taxies.biz| 5335-8130",
          "Source url": "http://www.taxies.biz/page-5b335e813069b81dfce4b6e4a8634c82.html",
          "Target url": "https://mexicolife.com/",
          "Anchor": "buceriashomes.com",
          "External links": "10159",
          "Internal links": "12",
          "Nofollow": "false",
          "Sponsored": "false",
          "Ugc": "false",
          "Text": "true",
          "Frame": "false",
          "Form": "false",
          "Image": "false",
          "Sitewide": "false",
          "First seen": "2026-04-22",
          "Last seen": "2026-04-22",
          "New link": "true",
          "Lost link": "false"
        },
        {
          "Page ascore": "0",
          "Source title": "Where to buy 🚀 aged domains and backlinks 🔥 | 5456-0507",
          "Source url": "https://websiterace.com/bf5456ac05075e0ae6bfd284530451c1-l/",
          "Target url": "https://mexicolife.com/",
          "Anchor": "homeinmexico.com",
          "External links": "9003",
          "Internal links": "12",
          "Nofollow": "false",
          "Sponsored": "false",
          "Ugc": "false",
          "Text": "true",
          "Frame": "false",
          "Form": "false",
          "Image": "false",
          "Sitewide": "false",
          "First seen": "2026-04-22",
          "Last seen": "2026-04-30",
          "New link": "true",
          "Lost link": "false"
        },
        {
          "Page ascore": "0",
          "Source title": "Where to buy 🚀 aged domains and backlinks 🔥 from www.queries.co.in| 6529-0423",
          "Source url": "http://www.queries.co.in/page-6b52bb90d4236e4c69a0221894141852.html",
          "Target url": "https://mexicolife.com/",
          "Anchor": "elementsofmexico.com",
          "External links": "10157",
          "Internal links": "12",
          "Nofollow": "false",
          "Sponsored": "false",
          "Ugc": "false",
          "Text": "true",
          "Frame": "false",
          "Form": "false",
          "Image": "false",
          "Sitewide": "false",
          "First seen": "2026-04-21",
          "Last seen": "2026-04-21",
          "New link": "true",
          "Lost link": "false"
        },
        {
          "Page ascore": "0",
          "Source title": "Where to buy 🚀 aged domains and backlinks 🔥 from www.hebagh.cv| 0370-5882",
          "Source url": "http://www.hebagh.cv/page-0b3fc7f0588fcac214841501c1f573e5.html",
          "Target url": "https://mexicolife.com/",
          "Anchor": "homeinmexico.com",
          "External links": "10159",
          "Internal links": "12",
          "Nofollow": "false",
          "Sponsored": "false",
          "Ugc": "false",
          "Text": "true",
          "Frame": "false",
          "Form": "false",
          "Image": "false",
          "Sitewide": "false",
          "First seen": "2026-04-21",
          "Last seen": "2026-04-21",
          "New link": "true",
          "Lost link": "false"
        },
        {
          "Page ascore": "0",
          "Source title": "Where to buy 🚀 aged domains and backlinks 🔥 from www.thirty.co.in| 0433-4886",
          "Source url": "http://www.thirty.co.in/page-0433488a64ac643080dec84f998e8f89.html",
          "Target url": "https://mexicolife.com/",
          "Anchor": "ergmex.com",
          "External links": "10160",
          "Internal links": "12",
          "Nofollow": "false",
          "Sponsored": "false",
          "Ugc": "false",
          "Text": "true",
          "Frame": "false",
          "Form": "false",
          "Image": "false",
          "Sitewide": "false",
          "First seen": "2026-04-21",
          "Last seen": "2026-04-21",
          "New link": "true",
          "Lost link": "false"
        },
        {
          "Page ascore": "0",
          "Source title": "Where to buy 🚀 aged domains and backlinks 🔥 from www.cheapsmmprovider.online| 6529-0423",
          "Source url": "http://www.cheapsmmprovider.online/page-6b52bb90d4236e4c69a0221894141852.html",
          "Target url": "https://mexicolife.com/",
          "Anchor": "elementsofmexico.com",
          "External links": "10157",
          "Internal links": "12",
          "Nofollow": "false",
          "Sponsored": "false",
          "Ugc": "false",
          "Text": "true",
          "Frame": "false",
          "Form": "false",
          "Image": "false",
          "Sitewide": "false",
          "First seen": "2026-04-21",
          "Last seen": "2026-04-21",
          "New link": "true",
          "Lost link": "false"
        }
      ]
    },
    {
      "filename": "mexicolife.com-organic.Positions-us-20260506-2026-05-07T07_08_15Z.csv",
      "competitorId": "www-mexicolife-com",
      "type": "positions",
      "rowCount": 2904,
      "topRows": [
        {
          "Keyword": "nuevo vallarta mexico",
          "Position": "1",
          "Previous position": "1",
          "Search Volume": "1000",
          "Keyword Difficulty": "20",
          "CPC": "0.82",
          "URL": "https://www.mexicolife.com/nuevo-vallarta-condos-for-sale.php",
          "Traffic": "124",
          "Traffic (%)": "3.4",
          "Traffic Cost": "101.00",
          "Competition": "0.15",
          "Number of Results": "104",
          "Trends": "[46,100,37,37,37,46,52,52,46,46,46,52]",
          "Timestamp": "2026-04-21",
          "SERP Features by Keyword": "Knowledge panel, Sitelinks, Video, Image, Video Carousel, Related searches, Short videos, Things to know, AI overview",
          "Keyword Intents": "informational",
          "Position Type": "Things to know"
        },
        {
          "Keyword": "puerto vallarta real estate",
          "Position": "4",
          "Previous position": "4",
          "Search Volume": "3600",
          "Keyword Difficulty": "43",
          "CPC": "0.20",
          "URL": "https://www.mexicolife.com/old-town-vallarta.php",
          "Traffic": "108",
          "Traffic (%)": "2.96",
          "Traffic Cost": "21.00",
          "Competition": "0.44",
          "Number of Results": "3540000",
          "Trends": "[81,81,66,54,66,54,66,54,43,36,36,28]",
          "Timestamp": "2026-05-03",
          "SERP Features by Keyword": "Sitelinks, Video, Image, People also ask, Related searches",
          "Keyword Intents": "commercial",
          "Position Type": "Organic"
        },
        {
          "Keyword": "condos for sale in puerto vallarta mexico",
          "Position": "4",
          "Previous position": "4",
          "Search Volume": "1000",
          "Keyword Difficulty": "5",
          "CPC": "0.24",
          "URL": "https://www.mexicolife.com/puerto-vallarta-condos-for-sale.php",
          "Traffic": "65",
          "Traffic (%)": "1.78",
          "Traffic Cost": "15.00",
          "Competition": "0.41",
          "Number of Results": "436000",
          "Trends": "[62,81,81,100,45,45,62,55,45,45,45,81]",
          "Timestamp": "2026-04-24",
          "SERP Features by Keyword": "Ads bottom, People also ask, Related searches",
          "Keyword Intents": "transactional",
          "Position Type": "Organic"
        },
        {
          "Keyword": "puerto vallarta real estate condos for sale",
          "Position": "2",
          "Previous position": "2",
          "Search Volume": "480",
          "Keyword Difficulty": "10",
          "CPC": "0.24",
          "URL": "https://www.mexicolife.com/puerto-vallarta-condos-for-sale.php",
          "Traffic": "63",
          "Traffic (%)": "1.73",
          "Traffic Cost": "15.00",
          "Competition": "0.41",
          "Number of Results": "346000",
          "Trends": "[5,7,4,3,11,25,100,37,68,52,5,5]",
          "Timestamp": "2026-05-06",
          "SERP Features by Keyword": "Video, People also ask, Related searches",
          "Keyword Intents": "transactional",
          "Position Type": "Organic"
        },
        {
          "Keyword": "homes for sale in puerto vallarta mexico",
          "Position": "7",
          "Previous position": "7",
          "Search Volume": "1300",
          "Keyword Difficulty": "17",
          "CPC": "0.19",
          "URL": "https://www.mexicolife.com/puerto-vallarta-real-estate.php",
          "Traffic": "39",
          "Traffic (%)": "1.07",
          "Traffic Cost": "7.00",
          "Competition": "0.36",
          "Number of Results": "3300000",
          "Trends": "[24,8,18,16,13,8,100,8,10,16,29,7]",
          "Timestamp": "2026-03-14",
          "SERP Features by Keyword": "Video, Related searches",
          "Keyword Intents": "transactional",
          "Position Type": "Organic"
        },
        {
          "Keyword": "grand venetian puerto vallarta",
          "Position": "3",
          "Previous position": "3",
          "Search Volume": "480",
          "Keyword Difficulty": "17",
          "CPC": "1.31",
          "URL": "https://www.mexicolife.com/grand-venetian-condos.php",
          "Traffic": "39",
          "Traffic (%)": "1.07",
          "Traffic Cost": "51.00",
          "Competition": "0.67",
          "Number of Results": "0",
          "Trends": "[45,45,45,30,30,24,36,30,20,24,24,24]",
          "Timestamp": "2026-03-14",
          "SERP Features by Keyword": "Sitelinks, Video, Image, Related searches",
          "Keyword Intents": "commercial",
          "Position Type": "Organic"
        },
        {
          "Keyword": "buy a house in puerto vallarta",
          "Position": "4",
          "Previous position": "4",
          "Search Volume": "590",
          "Keyword Difficulty": "15",
          "CPC": "0.19",
          "URL": "https://www.mexicolife.com/puerto-vallarta-real-estate.php",
          "Traffic": "38",
          "Traffic (%)": "1.04",
          "Traffic Cost": "7.00",
          "Competition": "0.36",
          "Number of Results": "110",
          "Trends": "[16,5,52,25,100,37,46,13,5,20,11,13]",
          "Timestamp": "2026-03-27",
          "SERP Features by Keyword": "Video, Related searches",
          "Keyword Intents": "transactional",
          "Position Type": "Organic"
        },
        {
          "Keyword": "condominiums for sale in puerto vallarta mexico",
          "Position": "3",
          "Previous position": "3",
          "Search Volume": "390",
          "Keyword Difficulty": "7",
          "CPC": "0.24",
          "URL": "https://www.mexicolife.com/puerto-vallarta-condos-for-sale.php",
          "Traffic": "31",
          "Traffic (%)": "0.85",
          "Traffic Cost": "7.00",
          "Competition": "0.41",
          "Number of Results": "910000",
          "Trends": "[16,10,6,5,16,36,13,55,100,76,8,8]",
          "Timestamp": "2026-03-22",
          "SERP Features by Keyword": "Local pack, Image, Related searches",
          "Keyword Intents": "transactional",
          "Position Type": "Organic"
        },
        {
          "Keyword": "condo for sale puerto vallarta",
          "Position": "3",
          "Previous position": "3",
          "Search Volume": "390",
          "Keyword Difficulty": "5",
          "CPC": "0.24",
          "URL": "https://www.mexicolife.com/puerto-vallarta-condos-for-sale-zona-romantica.php",
          "Traffic": "31",
          "Traffic (%)": "0.85",
          "Traffic Cost": "7.00",
          "Competition": "0.41",
          "Number of Results": "449000",
          "Trends": "[15,54,54,36,44,44,54,23,29,44,29,44]",
          "Timestamp": "2026-04-30",
          "SERP Features by Keyword": "Video, Image, People also ask, Related searches",
          "Keyword Intents": "transactional",
          "Position Type": "Organic"
        },
        {
          "Keyword": "condos in puerto vallarta",
          "Position": "2",
          "Previous position": "2",
          "Search Volume": "390",
          "Keyword Difficulty": "6",
          "CPC": "0.70",
          "URL": "https://www.mexicolife.com/beachfront-condos-for-sale-in-puerto-vallarta.php",
          "Traffic": "31",
          "Traffic (%)": "0.85",
          "Traffic Cost": "21.00",
          "Competition": "0.55",
          "Number of Results": "715000",
          "Trends": "[81,67,67,44,44,19,29,23,19,44,36,44]",
          "Timestamp": "2026-03-18",
          "SERP Features by Keyword": "Local pack, Video, Image, Related searches",
          "Keyword Intents": "commercial",
          "Position Type": "Organic"
        },
        {
          "Keyword": "puerto vallarta condos for sale",
          "Position": "9",
          "Previous position": "9",
          "Search Volume": "1300",
          "Keyword Difficulty": "10",
          "CPC": "0.24",
          "URL": "https://www.mexicolife.com/puerto-vallarta-condos-for-sale-zona-romantica.php",
          "Traffic": "31",
          "Traffic (%)": "0.85",
          "Traffic Cost": "7.00",
          "Competition": "0.41",
          "Number of Results": "117",
          "Trends": "[82,44,34,55,55,55,55,30,30,24,34,20]",
          "Timestamp": "2026-04-21",
          "SERP Features by Keyword": "Video, Image, Related searches",
          "Keyword Intents": "transactional",
          "Position Type": "Organic"
        },
        {
          "Keyword": "condos for sale puerto vallarta",
          "Position": "3",
          "Previous position": "3",
          "Search Volume": "390",
          "Keyword Difficulty": "4",
          "CPC": "0.24",
          "URL": "https://www.mexicolife.com/beachfront-condos-for-sale-in-puerto-vallarta.php",
          "Traffic": "31",
          "Traffic (%)": "0.85",
          "Traffic Cost": "7.00",
          "Competition": "0.41",
          "Number of Results": "124",
          "Trends": "[20,30,16,13,8,8,20,7,8,7,4,36]",
          "Timestamp": "2026-03-31",
          "SERP Features by Keyword": "Image, Related searches",
          "Keyword Intents": "transactional",
          "Position Type": "Organic"
        },
        {
          "Keyword": "condo for sale in puerto vallarta",
          "Position": "3",
          "Previous position": "3",
          "Search Volume": "390",
          "Keyword Difficulty": "6",
          "CPC": "0.24",
          "URL": "https://www.mexicolife.com/puerto-vallarta-condos-for-sale-zona-romantica.php",
          "Traffic": "31",
          "Traffic (%)": "0.85",
          "Traffic Cost": "7.00",
          "Competition": "0.41",
          "Number of Results": "648000",
          "Trends": "[36,66,66,54,66,54,66,54,44,54,36,54]",
          "Timestamp": "2026-04-09",
          "SERP Features by Keyword": "Video, Related searches",
          "Keyword Intents": "transactional",
          "Position Type": "Organic"
        },
        {
          "Keyword": "condos for sale in puerto vallarta",
          "Position": "3",
          "Previous position": "4",
          "Search Volume": "390",
          "Keyword Difficulty": "9",
          "CPC": "0.24",
          "URL": "https://www.mexicolife.com/puerto-vallarta-condos-for-sale-zona-romantica.php",
          "Traffic": "31",
          "Traffic (%)": "0.85",
          "Traffic Cost": "7.00",
          "Competition": "0.41",
          "Number of Results": "367000",
          "Trends": "[31,16,16,16,13,37,16,46,8,20,5,25]",
          "Timestamp": "2026-05-06",
          "SERP Features by Keyword": "Video, Image, Ads bottom, People also ask, Related searches",
          "Keyword Intents": "transactional",
          "Position Type": "Organic"
        },
        {
          "Keyword": "sayulita real estate",
          "Position": "6",
          "Previous position": "6",
          "Search Volume": "880",
          "Keyword Difficulty": "3",
          "CPC": "0.07",
          "URL": "https://www.mexicolife.com/sayulita-mls.php?p=2",
          "Traffic": "30",
          "Traffic (%)": "0.82",
          "Traffic Cost": "2.00",
          "Competition": "0.45",
          "Number of Results": "327000",
          "Trends": "[81,62,81,55,55,55,55,45,36,45,30,36]",
          "Timestamp": "2026-04-03",
          "SERP Features by Keyword": "Video, Image, People also ask, Related searches",
          "Keyword Intents": "commercial",
          "Position Type": "Organic"
        },
        {
          "Keyword": "homes for sale in puerto vallarta",
          "Position": "7",
          "Previous position": "7",
          "Search Volume": "1000",
          "Keyword Difficulty": "18",
          "CPC": "0.19",
          "URL": "https://www.mexicolife.com/puerto-vallarta-real-estate.php",
          "Traffic": "30",
          "Traffic (%)": "0.82",
          "Traffic Cost": "5.00",
          "Competition": "0.36",
          "Number of Results": "1990000",
          "Trends": "[66,54,41,41,41,54,54,36,30,24,20,16]",
          "Timestamp": "2026-04-06",
          "SERP Features by Keyword": "Video, Related searches",
          "Keyword Intents": "transactional",
          "Position Type": "Organic"
        },
        {
          "Keyword": "houses for sale in mexico under $100 000",
          "Position": "1",
          "Previous position": "1",
          "Search Volume": "210",
          "Keyword Difficulty": "1",
          "CPC": "0.77",
          "URL": "https://www.mexicolife.com/pool/under-100000/",
          "Traffic": "27",
          "Traffic (%)": "0.74",
          "Traffic Cost": "20.00",
          "Competition": "0.08",
          "Number of Results": "43800000",
          "Trends": "[34,53,53,65,65,100,100,100,65,65,65,81]",
          "Timestamp": "2026-04-03",
          "SERP Features by Keyword": "Video, Related searches, AI overview",
          "Keyword Intents": "informational, transactional",
          "Position Type": "Organic"
        },
        {
          "Keyword": "amapas puerto vallarta",
          "Position": "1",
          "Previous position": "1",
          "Search Volume": "110",
          "Keyword Difficulty": "5",
          "CPC": "1.62",
          "URL": "https://www.mexicolife.com/amapas-puerto-vallarta-for-sale.php",
          "Traffic": "27",
          "Traffic (%)": "0.74",
          "Traffic Cost": "43.00",
          "Competition": "0.38",
          "Number of Results": "109",
          "Trends": "[53,53,53,42,34,26,42,42,34,42,42,53]",
          "Timestamp": "2026-04-26",
          "SERP Features by Keyword": "Knowledge panel, Sitelinks, Video, Image, Video Carousel, People also ask, Related searches",
          "Keyword Intents": "informational, transactional",
          "Position Type": "Knowledge panel"
        },
        {
          "Keyword": "puerto vallarta mexico condos",
          "Position": "2",
          "Previous position": "2",
          "Search Volume": "210",
          "Keyword Difficulty": "5",
          "CPC": "0.70",
          "URL": "https://www.mexicolife.com/puerto-vallarta-condos-for-sale.php",
          "Traffic": "27",
          "Traffic (%)": "0.74",
          "Traffic Cost": "18.00",
          "Competition": "0.55",
          "Number of Results": "614000",
          "Trends": "[11,0,35,66,100,35,18,28,44,44,1,6]",
          "Timestamp": "2026-04-21",
          "SERP Features by Keyword": "Local pack, Video, Image, Related searches",
          "Keyword Intents": "commercial",
          "Position Type": "Organic"
        },
        {
          "Keyword": "houses for sale in puerto vallarta under $100k",
          "Position": "1",
          "Previous position": "1",
          "Search Volume": "110",
          "Keyword Difficulty": "0",
          "CPC": "0.07",
          "URL": "https://www.mexicolife.com/pool/under-100000/",
          "Traffic": "27",
          "Traffic (%)": "0.74",
          "Traffic Cost": "1.00",
          "Competition": "0.08",
          "Number of Results": "16200",
          "Trends": "[100,100,28,21,15,28,34,21,28,34,28,21]",
          "Timestamp": "2026-03-29",
          "SERP Features by Keyword": "Video, People also ask, Related searches",
          "Keyword Intents": "transactional",
          "Position Type": "Organic"
        },
        {
          "Keyword": "mexico mortgage calculator",
          "Position": "1",
          "Previous position": "1",
          "Search Volume": "110",
          "Keyword Difficulty": "2",
          "CPC": "0.00",
          "URL": "https://www.mexicolife.com/mexico-mortgage-calculator.php",
          "Traffic": "27",
          "Traffic (%)": "0.74",
          "Traffic Cost": "0.00",
          "Competition": "0",
          "Number of Results": "19100000",
          "Trends": "[29,29,22,22,22,29,29,29,14,18,14,14]",
          "Timestamp": "2026-05-02",
          "SERP Features by Keyword": "Video, People also ask, Related searches",
          "Keyword Intents": "commercial, informational",
          "Position Type": "Organic"
        },
        {
          "Keyword": "houses for sale in puerto vallarta under $100 k",
          "Position": "1",
          "Previous position": "1",
          "Search Volume": "110",
          "Keyword Difficulty": "0",
          "CPC": "0.07",
          "URL": "https://www.mexicolife.com/pool/under-100000/",
          "Traffic": "27",
          "Traffic (%)": "0.74",
          "Traffic Cost": "1.00",
          "Competition": "0.08",
          "Number of Results": "107",
          "Trends": "[80,80,52,42,100,80,66,33,52,0,9,0]",
          "Timestamp": "2026-03-20",
          "SERP Features by Keyword": "Video, Related searches",
          "Keyword Intents": "transactional",
          "Position Type": "Organic"
        },
        {
          "Keyword": "nuevo vallarta real estate",
          "Position": "2",
          "Previous position": "2",
          "Search Volume": "210",
          "Keyword Difficulty": "0",
          "CPC": "0.10",
          "URL": "https://www.mexicolife.com/nuevo-vallarta-real-estate.php",
          "Traffic": "27",
          "Traffic (%)": "0.74",
          "Traffic Cost": "2.00",
          "Competition": "0.43",
          "Number of Results": "546",
          "Trends": "[53,53,53,53,66,53,66,82,53,43,43,66]",
          "Timestamp": "2026-04-28",
          "SERP Features by Keyword": "Video, Image, People also ask, Related searches",
          "Keyword Intents": "commercial",
          "Position Type": "Organic"
        },
        {
          "Keyword": "cheap homes for sale in mexico",
          "Position": "3",
          "Previous position": "3",
          "Search Volume": "320",
          "Keyword Difficulty": "16",
          "CPC": "0.98",
          "URL": "https://www.mexicolife.com/pool/under-100000/",
          "Traffic": "26",
          "Traffic (%)": "0.71",
          "Traffic Cost": "25.00",
          "Competition": "0.05",
          "Number of Results": "83600000",
          "Trends": "[72,48,39,39,21,21,39,26,21,17,17,21]",
          "Timestamp": "2026-05-05",
          "SERP Features by Keyword": "Video, People also ask, Related searches",
          "Keyword Intents": "transactional",
          "Position Type": "Organic"
        },
        {
          "Keyword": "cheap houses for sale in mexico",
          "Position": "3",
          "Previous position": "0",
          "Search Volume": "320",
          "Keyword Difficulty": "9",
          "CPC": "0.98",
          "URL": "https://www.mexicolife.com/pool/under-100000/",
          "Traffic": "26",
          "Traffic (%)": "0.71",
          "Traffic Cost": "25.00",
          "Competition": "0.05",
          "Number of Results": "71300000",
          "Trends": "[54,54,54,54,44,44,54,44,44,29,29,36]",
          "Timestamp": "2026-05-06",
          "SERP Features by Keyword": "Video, People also ask, Related searches",
          "Keyword Intents": "transactional",
          "Position Type": "Organic"
        }
      ]
    }
  ]
}